med_metrics/__init__.py
med_metrics/bootstrap.py
med_metrics/compatibility_metrics.py
med_metrics/curves.py
med_metrics/metrics.py
med_metrics/utils.py
med_metrics-0.0.6.dist-info/licenses/LICENSE
tests/__init__.py
tests/test_compatibility_metrics.py
tests/test_metrics.py
med_metrics-0.0.6.dist-info/METADATA
med_metrics-0.0.6.dist-info/WHEEL
med_metrics-0.0.6.dist-info/top_level.txt
med_metrics-0.0.6.dist-info/RECORD
