Metadata-Version: 2.4
Name: med_metrics
Version: 0.0.6
Summary: Custom ML metrics for medical applications
Home-page: https://github.com/eotles/med_metrics
Author: Erkin Ötleş
Author-email: hi@eotles.com
License-File: LICENSE
Requires-Dist: numpy
Requires-Dist: scikit-learn
Requires-Dist: matplotlib
Dynamic: author
Dynamic: author-email
Dynamic: description
Dynamic: description-content-type
Dynamic: home-page
Dynamic: license-file
Dynamic: requires-dist
Dynamic: summary
